[
  {
    "resultId": "347",
    "resultName": "Tremendous Fire",
    "description": "",
    "isGlitch": false,
    "rules": [
      {
        "material1": [
          "346"
        ],
        "material2": [
          "346"
        ]
      }
    ]
  },
  {
    "resultId": "348",
    "resultName": "Swords of Revealing Light",
    "description": "",
    "isGlitch": false,
    "rules": [
      {
        "material1": [
          "350"
        ],
        "material2": [
          "669"
        ]
      }
    ]
  },
  {
    "resultId": "357",
    "resultName": "Yamadron",
    "description": "",
    "isGlitch": false,
    "rules": [
      {
        "material1": [
          "298"
        ],
        "material2": [
          "318"
        ]
      }
    ]
  },
  {
    "resultId": "375",
    "resultName": "Dungeon Worm",
    "description": "",
    "isGlitch": false,
    "rules": [
      {
        "material1": [
          "366"
        ],
        "material2": [
          "393"
        ]
      }
    ]
  },
  {
    "resultId": "376",
    "resultName": "Monster Tamer",
    "description": "",
    "isGlitch": false,
    "rules": [
      {
        "material1": [
          "338"
        ],
        "material2": [
          "434"
        ]
      }
    ]
  },
  {
    "resultId": "377",
    "resultName": "Ryu-kishin Powered",
    "description": "\"Ryu-kishin\" + Dark (Mercury)",
    "isGlitch": false,
    "rules": [
      {
        "material1": [
          "005"
        ],
        "material2": [
          "017",
          "018",
          "019",
          "020",
          "021",
          "034",
          "104",
          "115",
          "129",
          "179",
          "190",
          "220",
          "253",
          "259",
          "268",
          "387",
          "530",
          "574",
          "578",
          "628"
        ]
      }
    ]
  },
  {
    "resultId": "386",
    "resultName": "Harpie's Pet Dragon",
    "description": "\"Harpie Lady\" + Dragon",
    "isGlitch": false,
    "rules": [
      {
        "material1": [
          "062"
        ],
        "material2": [
          "004",
          "007",
          "010",
          "011",
          "031",
          "073",
          "081",
          "094",
          "097",
          "122",
          "138",
          "168",
          "200",
          "296",
          "298",
          "353",
          "357",
          "409",
          "424",
          "425",
          "448",
          "545",
          "555",
          "561",
          "603",
          "712"
        ]
      }
    ]
  },
  {
    "resultId": "390",
    "resultName": "Launcher Spider",
    "description": "",
    "isGlitch": false,
    "rules": [
      {
        "material1": [
          "367"
        ],
        "material2": [
          "658"
        ]
      }
    ]
  },
  {
    "resultId": "392",
    "resultName": "Metalzoa",
    "description": "",
    "isGlitch": false,
    "rules": [
      {
        "material1": [
          "391"
        ],
        "material2": [
          "658"
        ]
      }
    ]
  },
  {
    "resultId": "401",
    "resultName": "Ushi Oni",
    "description": "Pot/Jar + Spellcaster",
    "isGlitch": false,
    "rules": [
      {
        "material1": [
          "040"
        ],
        "material2": [
          "017",
          "018",
          "019",
          "020",
          "021",
          "034",
          "104",
          "115",
          "129",
          "179",
          "190",
          "220",
          "253",
          "259",
          "268",
          "387",
          "530",
          "551",
          "574",
          "578",
          "628"
        ]
      },
      {
        "material1": [
          "167",
          "558",
          "591"
        ],
        "material2": [
          "017",
          "018",
          "019",
          "020",
          "021",
          "034",
          "104",
          "115",
          "179",
          "190",
          "220",
          "259",
          "268",
          "387",
          "578"
        ]
      }
    ]
  },
  {
    "resultId": "404",
    "resultName": "Tatsunootoshigo",
    "description": "",
    "isGlitch": false,
    "rules": [
      {
        "material1": [
          "247",
          "436",
          "546"
        ],
        "material2": [
          "046",
          "047",
          "061",
          "065",
          "091",
          "113",
          "121",
          "155",
          "159",
          "163",
          "187",
          "188",
          "189",
          "201",
          "202",
          "212",
          "248",
          "252",
          "255",
          "282",
          "384",
          "481",
          "496",
          "527",
          "541",
          "587",
          "598",
          "604",
          "607",
          "629",
          "642"
        ]
      },
      {
        "material1": [
          "251",
          "626"
        ],
        "material2": [
          "155",
          "159",
          "163",
          "187",
          "212",
          "252",
          "384",
          "496",
          "541",
          "587",
          "607"
        ]
      }
    ]
  },
  {
    "resultId": "409",
    "resultName": "Metal Dragon",
    "description": "Dragon + Machine",
    "isGlitch": false,
    "rules": [
      {
        "material1": [
          "004"
        ],
        "material2": [
          "124",
          "275",
          "283",
          "286",
          "297",
          "355",
          "388",
          "394",
          "405",
          "406",
          "408",
          "410",
          "411",
          "412",
          "413",
          "414",
          "416",
          "417",
          "418",
          "419",
          "420",
          "421",
          "422",
          "423",
          "438",
          "441",
          "508",
          "512",
          "513",
          "514",
          "544",
          "557",
          "580",
          "585",
          "643",
          "648",
          "658"
        ]
      },
      {
        "material1": [
          "007",
          "010",
          "031",
          "073",
          "094",
          "097",
          "122",
          "168",
          "200",
          "296",
          "298",
          "353",
          "357",
          "425",
          "448",
          "545",
          "555",
          "561",
          "603",
          "712"
        ],
        "material2": [
          "124",
          "275",
          "283",
          "286",
          "297",
          "355",
          "388",
          "394",
          "405",
          "406",
          "408",
          "410",
          "411",
          "412",
          "413",
          "414",
          "416",
          "417",
          "418",
          "419",
          "420",
          "421",
          "422",
          "423",
          "438",
          "441",
          "508",
          "512",
          "513",
          "514",
          "544",
          "557",
          "580",
          "585",
          "643",
          "648"
        ]
      },
      {
        "material1": [
          "011",
          "081"
        ],
        "material2": [
          "441",
          "508"
        ]
      },
      {
        "material1": [
          "138"
        ],
        "material2": [
          "124",
          "275",
          "286",
          "355",
          "388",
          "408",
          "413",
          "419",
          "423",
          "438",
          "441",
          "508",
          "513",
          "648"
        ]
      }
    ]
  },
  {
    "resultId": "412",
    "resultName": "Giga-tech Wolf",
    "description": "Beast + Machine",
    "isGlitch": false,
    "rules": [
      {
        "material1": [
          "113",
          "121",
          "188",
          "189",
          "202",
          "255",
          "262",
          "481",
          "527",
          "598",
          "604",
          "629",
          "642"
        ],
        "material2": [
          "283",
          "394",
          "406",
          "410",
          "411",
          "414",
          "416",
          "418",
          "420",
          "421",
          "422",
          "544",
          "580",
          "585"
        ]
      }
    ]
  },
  {
    "resultId": "413",
    "resultName": "Cyber Soldier",
    "description": "",
    "isGlitch": false,
    "rules": [
      {
        "material1": [
          "283",
          "297",
          "394",
          "405",
          "406",
          "410",
          "411",
          "412",
          "414",
          "416",
          "418",
          "420",
          "421",
          "422",
          "512",
          "514",
          "544",
          "557",
          "580",
          "585",
          "643"
        ],
        "material2": [
          "041",
          "100",
          "107",
          "110",
          "118",
          "120",
          "138",
          "147",
          "151",
          "156",
          "160",
          "161",
          "165",
          "166",
          "172",
          "182",
          "185",
          "195",
          "214",
          "224",
          "225",
          "226",
          "231",
          "235",
          "236",
          "239",
          "250",
          "256",
          "262",
          "266",
          "267",
          "280",
          "290",
          "293",
          "294",
          "299",
          "352",
          "354",
          "362",
          "399",
          "469",
          "502",
          "553",
          "559",
          "586",
          "635",
          "641",
          "649"
        ]
      }
    ]
  },
  {
    "resultId": "423",
    "resultName": "Dice Armadillo",
    "description": "",
    "isGlitch": false,
    "rules": [
      {
        "material1": [
          "046",
          "047",
          "061",
          "065",
          "091",
          "201",
          "248",
          "528",
          "597"
        ],
        "material2": [
          "275",
          "283",
          "286",
          "297",
          "355",
          "394",
          "405",
          "406",
          "410",
          "411",
          "412",
          "413",
          "414",
          "416",
          "418",
          "420",
          "421",
          "422",
          "438",
          "512",
          "514",
          "544",
          "557",
          "580",
          "585",
          "643",
          "648"
        ]
      },
      {
        "material1": [
          "113",
          "121",
          "188",
          "189",
          "202",
          "255",
          "282",
          "481",
          "527",
          "598",
          "604",
          "629",
          "642"
        ],
        "material2": [
          "275",
          "286",
          "297",
          "355",
          "405",
          "412",
          "413",
          "438",
          "512",
          "514",
          "557",
          "643",
          "648"
        ]
      }
    ]
  },
  {
    "resultId": "425",
    "resultName": "Thunder Dragon",
    "description": "Thunder + Dragon",
    "isGlitch": false,
    "rules": [
      {
        "material1": [
          "045",
          "191",
          "211",
          "459",
          "460",
          "461",
          "462",
          "463",
          "537",
          "610"
        ],
        "material2": [
          "004",
          "007",
          "010",
          "031",
          "122",
          "138",
          "168",
          "200",
          "296",
          "298",
          "353",
          "561",
          "603"
        ]
      }
    ]
  },
  {
    "resultId": "426",
    "resultName": "Stone D.",
    "description": "Rock + Dragon",
    "isGlitch": false,
    "rules": [
      {
        "material1": [
          "028",
          "074",
          "167",
          "237",
          "257",
          "263",
          "366",
          "454",
          "455",
          "456",
          "457",
          "505",
          "515",
          "516",
          "517",
          "558",
          "591",
          "623",
          "632"
        ],
        "material2": [
          "004",
          "007",
          "010",
          "011",
          "031",
          "073",
          "081",
          "094",
          "097",
          "122",
          "138",
          "168",
          "200",
          "296",
          "298",
          "353",
          "357",
          "409",
          "424",
          "425",
          "448",
          "545",
          "555",
          "561",
          "603",
          "712"
        ]
      },
      {
        "material1": [
          "244"
        ],
        "material2": [
          "004",
          "007",
          "010",
          "011",
          "031",
          "073",
          "081",
          "094",
          "097",
          "122",
          "168",
          "200",
          "296",
          "298",
          "353",
          "357",
          "409",
          "424",
          "425",
          "448",
          "545",
          "555",
          "561",
          "603",
          "712"
        ]
      }
    ]
  },
  {
    "resultId": "430",
    "resultName": "Water Magician",
    "description": "",
    "isGlitch": false,
    "rules": [
      {
        "material1": [
          "432"
        ],
        "material2": [
          "446"
        ]
      }
    ]
  },
  {
    "resultId": "431",
    "resultName": "Ice Water",
    "description": "",
    "isGlitch": false,
    "rules": [
      {
        "material1": [
          "247",
          "436"
        ],
        "material2": [
          "002",
          "129",
          "180",
          "192",
          "243",
          "253",
          "260",
          "395",
          "428",
          "429",
          "432",
          "530",
          "574",
          "592",
          "600",
          "612",
          "628"
        ]
      }
    ]
  },
  {
    "resultId": "433",
    "resultName": "Ancient Elf",
    "description": "",
    "isGlitch": false,
    "rules": [
      {
        "material1": [
          "428"
        ],
        "material2": [
          "658"
        ]
      }
    ]
  }
]
